Endtrz/Endtrz.py
Endtrz/Endtrzcontext.py
Endtrz/__init__.py
Endtrz/__main__.py
Endtrz/exceptions.py
Endtrz/lateststamps.py
Endtrz/nodeiterator.py
Endtrz/py.typed
Endtrz/sectioniterator.py
Endtrz/structures.py
endtrz-2.1.dist-info/licenses/AUTHORS.md
endtrz-2.1.dist-info/licenses/LICENSE
endtrz-2.1.dist-info/METADATA
endtrz-2.1.dist-info/WHEEL
endtrz-2.1.dist-info/entry_points.txt
endtrz-2.1.dist-info/top_level.txt
endtrz-2.1.dist-info/RECORD
