Metadata-Version: 2.4
Name: Endtrz
Version: 2.1
Summary: Insta downloader of https://hasnainkk-07.vercel.appDownload video, images, stories from Instagram.
Home-page: https://Endtrz.github.io/
Author: Endtrz
Author-email: lord_izana@yahoo.com, dilshadhasnain89@gmail.com
License: MIT
Keywords: instagram,instagram-scraper,instagram-client,instagram-feed,downloader,videos,photos,pictures,instagram-user-photos,instagram-photos,instagram-metadata,instagram-downloader,instagram-stories
Classifier: Development Status :: 5 - Production/Stable
Classifier: Environment :: Console
Classifier: Intended Audience :: End Users/Desktop
Classifier: Intended Audience :: Developers
Classifier: License :: OSI Approved :: MIT License
Classifier: Operating System :: OS Independent
Classifier: Programming Language :: Python :: 3.9
Classifier: Programming Language :: Python :: 3.10
Classifier: Programming Language :: Python :: 3.11
Classifier: Programming Language :: Python :: 3.12
Classifier: Programming Language :: Python :: 3.13
Classifier: Programming Language :: Python :: 3 :: Only
Classifier: Topic :: Internet
Classifier: Topic :: Multimedia :: Graphics
Requires-Python: >=3.9
License-File: LICENSE
License-File: AUTHORS.md
Requires-Dist: requests>=2.25
Provides-Extra: browser-cookie3
Requires-Dist: browser_cookie3>=0.19.1; extra == "browser-cookie3"
Dynamic: author
Dynamic: author-email
Dynamic: classifier
Dynamic: description
Dynamic: home-page
Dynamic: keywords
Dynamic: license
Dynamic: license-file
Dynamic: provides-extra
Dynamic: requires-dist
Dynamic: requires-python
Dynamic: summary
